Metadata-Version: 2.1
Name: motioneye.eo
Version: 22.4.1
Summary: motioneye.eo, a multilingual web interface for motion.
Home-page: https://github.com/jmichault/motioneye.eo
Author: Calin Crisan, Jean Michault, ...
Author-email: author@example.com
License: GNU General Public License v3.0
Project-URL: Bug Tracker, https://github.com/jmichault/motioneye.eo/issues
Keywords: motion,video,surveillance,frontend
Classifier: Programming Language :: Python :: 3
Classifier: License :: OSI Approved :: GNU General Public License v3 (GPLv3)
Classifier: Operating System :: POSIX :: Linux
Requires-Python: >=3.7
License-File: LICENSE
Requires-Dist: tornado
Requires-Dist: jinja2
Requires-Dist: pillow
Requires-Dist: pycurl
Requires-Dist: babel
Requires-Dist: boto3
